cloe_snowflake_crawler/__init__.py
cloe_snowflake_crawler/main.py
cloe_snowflake_crawler/py.typed
cloe_snowflake_crawler/crawler/__init__.py
cloe_snowflake_crawler/crawler/snowflake_crawler.py
cloe_snowflake_crawler/templates/__init__.py
cloe_snowflake_crawler/templates/column_retrieve.sql.j2
cloe_snowflake_crawler/templates/schema_retrieve.sql.j2
cloe_snowflake_crawler/templates/table_retrieve.sql.j2
cloe_snowflake_crawler/utils/__init__.py
cloe_snowflake_crawler/utils/repository.py
cloe_snowflake_crawler/utils/restore_old_databases.py
cloe_snowflake_crawler/utils/template_env.py
cloe_snowflake_crawler-1.1.2.dist-info/METADATA
cloe_snowflake_crawler-1.1.2.dist-info/WHEEL
cloe_snowflake_crawler-1.1.2.dist-info/entry_points.txt
cloe_snowflake_crawler-1.1.2.dist-info/RECORD
