Metadata-Version: 2.4
Name: cloe-snowflake-crawler
Version: 1.1.2
Summary: This package contains the Snowflake Crawler. It can scan Snowflake database and return the information to python functions or write to disk using the CLOE metadata format.
Author-email: initions <ICSMC_EXT_PYPIORG@accenture.com>
License: MIT
Classifier: Development Status :: 5 - Production/Stable
Classifier: Environment :: Console
Classifier: Intended Audience :: Developers
Classifier: License :: OSI Approved :: MIT License
Classifier: Operating System :: OS Independent
Classifier: Programming Language :: Python :: 3
Classifier: Topic :: Database
Requires-Python: <3.12,>=3.11
Requires-Dist: cloe-metadata~=2.2.1
Requires-Dist: cloe-util-snowflake-connector~=1.0.5
Requires-Dist: pydantic~=2.11.7
Requires-Dist: snowflake~=1.7.0
Requires-Dist: typer[all]~=0.16.0
